{
  "id": "m2-pro-19c-32gb__gemma-4-26b-a4b-it__6bit__omlx-api",
  "hardware": "m2-pro-19c-32gb",
  "model": "gemma-4-26b-a4b-it",
  "quant": "6bit",
  "runtime": {
    "name": "oMLX",
    "version": "0.3.5.dev1",
    "backend": "MLX",
    "flags": "oMLX community API; latest linked row per context",
    "cache": "prefix"
  },
  "measurements": [
    {
      "depth": 1024,
      "pp": 285.6,
      "tg": 35.3,
      "ppLabel": "6bit PP",
      "tgLabel": "6bit TG",
      "source": {
        "url": "https://omlx.ai/benchmarks/hcu4wq3f",
        "upstreamId": "hcu4wq3f",
        "createdAt": "2026-04-09T22:28:11Z",
        "ttftMs": 3585.7,
        "peakMemoryGb": 19.99
      }
    },
    {
      "depth": 4096,
      "pp": 307.5,
      "tg": 32.4,
      "ppLabel": "6bit PP",
      "tgLabel": "6bit TG",
      "source": {
        "url": "https://omlx.ai/benchmarks/3t174c42",
        "upstreamId": "3t174c42",
        "createdAt": "2026-04-09T22:28:12Z",
        "ttftMs": 13320.3,
        "peakMemoryGb": 20.41
      }
    },
    {
      "depth": 16384,
      "pp": 304.5,
      "tg": 22.2,
      "ppLabel": "6bit PP",
      "tgLabel": "6bit TG",
      "source": {
        "url": "https://omlx.ai/benchmarks/j2an97r7",
        "upstreamId": "j2an97r7",
        "createdAt": "2026-04-09T13:16:56Z",
        "ttftMs": 53804.4,
        "peakMemoryGb": 20.94
      }
    },
    {
      "depth": 32768,
      "pp": 284.8,
      "tg": 11.2,
      "ppLabel": "6bit PP",
      "tgLabel": "6bit TG",
      "source": {
        "url": "https://omlx.ai/benchmarks/97issa5r",
        "upstreamId": "97issa5r",
        "createdAt": "2026-04-09T22:46:16Z",
        "ttftMs": 115045.1,
        "peakMemoryGb": 21.71
      }
    }
  ],
  "evidence": {
    "rawUrl": "https://omlx.ai/api/benchmarks",
    "rawFormat": "oMLX API JSONL mirror",
    "retrievedAt": "2026-07-05T02:54:04.151Z",
    "upstreamId": "97issa5r",
    "parserVersion": "tokenfeel-omlx-api/1",
    "rawRows": [
      "hcu4wq3f 2026-04-09T22:28:11Z ctx=1024 pp=285.6 tg=35.3 omlx=0.3.5.dev1 os=macOS 26.2 https://omlx.ai/benchmarks/hcu4wq3f",
      "3t174c42 2026-04-09T22:28:12Z ctx=4096 pp=307.5 tg=32.4 omlx=0.3.5.dev1 os=macOS 26.2 https://omlx.ai/benchmarks/3t174c42",
      "j2an97r7 2026-04-09T13:16:56Z ctx=16384 pp=304.5 tg=22.2 omlx=0.3.5.dev1 os=macOS 26.3.1 https://omlx.ai/benchmarks/j2an97r7",
      "97issa5r 2026-04-09T22:46:16Z ctx=32768 pp=284.8 tg=11.2 omlx=0.3.5.dev1 os=macOS 26.2 https://omlx.ai/benchmarks/97issa5r"
    ],
    "upstreamUrls": [
      "https://omlx.ai/benchmarks/hcu4wq3f",
      "https://omlx.ai/benchmarks/3t174c42",
      "https://omlx.ai/benchmarks/j2an97r7",
      "https://omlx.ai/benchmarks/97issa5r"
    ]
  },
  "benchmark": {
    "tool": "oMLX",
    "outputFormat": "community API",
    "latencyMode": "single-user prompt/decode",
    "metadata": {
      "upstream_rows_in_group": 5,
      "selected_depths": 4,
      "latest_upstream_id": "97issa5r",
      "latest_created_at": "2026-04-09T22:46:16Z",
      "selected_omlx_versions": "0.3.5.dev1",
      "selected_os_versions": "macOS 26.2, macOS 26.3.1"
    }
  },
  "topology": {
    "acceleratorCount": 1,
    "os": "macOS 26.2",
    "runtimeVersions": {
      "omlx": "0.3.5.dev1"
    }
  },
  "source": {
    "kind": "community-benchmark",
    "title": "oMLX gemma-4-26b-a4b-it on M2 Pro (19c) community benchmark",
    "url": "https://omlx.ai/benchmarks/97issa5r",
    "raw": "data/upstream/omlx-benchmarks.jsonl",
    "license": "Apache-2.0 project; submitted benchmark data attribution required",
    "notes": "Generated from https://omlx.ai/benchmarks. Measurements link to their selected upstream oMLX benchmark rows."
  },
  "submitter": "oMLX community",
  "date": "2026-04-09",
  "status": "community",
  "notes": "Generated from the oMLX community benchmark API import. 5 upstream row(s) were scraped for this hardware/model/quant group; the latest row at each context depth was selected for simulation. Selected depths may span oMLX or macOS versions, and each measurement links to its exact upstream row."
}
