{
  "id": "m5-max-40c-128gb__gemma-4-31b-it-oq4__4bit__omlx-api",
  "hardware": "m5-max-40c-128gb",
  "model": "gemma-4-31b-it-oq4",
  "quant": "4bit",
  "runtime": {
    "name": "oMLX",
    "version": "0.3.5.dev2",
    "backend": "MLX",
    "flags": "oMLX community API; latest linked row per context",
    "cache": "prefix"
  },
  "measurements": [
    {
      "depth": 1024,
      "pp": 655.1,
      "tg": 23.1,
      "ppLabel": "4bit PP",
      "tgLabel": "4bit TG",
      "source": {
        "url": "https://omlx.ai/benchmarks/cwz701zg",
        "upstreamId": "cwz701zg",
        "createdAt": "2026-04-11T11:03:33Z",
        "ttftMs": 1563.2,
        "peakMemoryGb": 18.11
      }
    },
    {
      "depth": 4096,
      "pp": 675.6,
      "tg": 22.2,
      "ppLabel": "4bit PP",
      "tgLabel": "4bit TG",
      "source": {
        "url": "https://omlx.ai/benchmarks/43slutlr",
        "upstreamId": "43slutlr",
        "createdAt": "2026-04-11T11:03:34Z",
        "ttftMs": 6063.2,
        "peakMemoryGb": 20.82
      }
    },
    {
      "depth": 8192,
      "pp": 653.8,
      "tg": 20.5,
      "ppLabel": "4bit PP",
      "tgLabel": "4bit TG",
      "source": {
        "url": "https://omlx.ai/benchmarks/uro6zorn",
        "upstreamId": "uro6zorn",
        "createdAt": "2026-04-11T11:03:35Z",
        "ttftMs": 12529.6,
        "peakMemoryGb": 26.28
      }
    },
    {
      "depth": 16384,
      "pp": 582.6,
      "tg": 17.6,
      "ppLabel": "4bit PP",
      "tgLabel": "4bit TG",
      "source": {
        "url": "https://omlx.ai/benchmarks/wxl6xasl",
        "upstreamId": "wxl6xasl",
        "createdAt": "2026-04-11T11:03:35Z",
        "ttftMs": 28123.8,
        "peakMemoryGb": 38.32
      }
    },
    {
      "depth": 32768,
      "pp": 534.8,
      "tg": 5.2,
      "ppLabel": "4bit PP",
      "tgLabel": "4bit TG",
      "source": {
        "url": "https://omlx.ai/benchmarks/pk4gwdwa",
        "upstreamId": "pk4gwdwa",
        "createdAt": "2026-04-11T11:03:36Z",
        "ttftMs": 61273.8,
        "peakMemoryGb": 63.18
      }
    },
    {
      "depth": 65536,
      "pp": 466.5,
      "tg": 6.3,
      "ppLabel": "4bit PP",
      "tgLabel": "4bit TG",
      "source": {
        "url": "https://omlx.ai/benchmarks/9r4qg09c",
        "upstreamId": "9r4qg09c",
        "createdAt": "2026-04-11T05:36:08Z",
        "ttftMs": 140495.2,
        "peakMemoryGb": 28.57
      }
    },
    {
      "depth": 131072,
      "pp": 317.7,
      "tg": 3,
      "ppLabel": "4bit PP",
      "tgLabel": "4bit TG",
      "source": {
        "url": "https://omlx.ai/benchmarks/uynajfqv",
        "upstreamId": "uynajfqv",
        "createdAt": "2026-04-07T14:38:12Z",
        "ttftMs": 412551.6,
        "peakMemoryGb": 37.56
      }
    }
  ],
  "evidence": {
    "rawUrl": "https://omlx.ai/api/benchmarks",
    "rawFormat": "oMLX API JSONL mirror",
    "retrievedAt": "2026-07-05T02:54:04.135Z",
    "upstreamId": "pk4gwdwa",
    "parserVersion": "tokenfeel-omlx-api/1",
    "rawRows": [
      "cwz701zg 2026-04-11T11:03:33Z ctx=1024 pp=655.1 tg=23.1 omlx=0.3.5.dev2 os=macOS 26.4.1 https://omlx.ai/benchmarks/cwz701zg",
      "43slutlr 2026-04-11T11:03:34Z ctx=4096 pp=675.6 tg=22.2 omlx=0.3.5.dev2 os=macOS 26.4.1 https://omlx.ai/benchmarks/43slutlr",
      "uro6zorn 2026-04-11T11:03:35Z ctx=8192 pp=653.8 tg=20.5 omlx=0.3.5.dev2 os=macOS 26.4.1 https://omlx.ai/benchmarks/uro6zorn",
      "wxl6xasl 2026-04-11T11:03:35Z ctx=16384 pp=582.6 tg=17.6 omlx=0.3.5.dev2 os=macOS 26.4.1 https://omlx.ai/benchmarks/wxl6xasl",
      "pk4gwdwa 2026-04-11T11:03:36Z ctx=32768 pp=534.8 tg=5.2 omlx=0.3.5.dev2 os=macOS 26.4.1 https://omlx.ai/benchmarks/pk4gwdwa",
      "9r4qg09c 2026-04-11T05:36:08Z ctx=65536 pp=466.5 tg=6.3 omlx=0.3.4 os=macOS 26.3.1 https://omlx.ai/benchmarks/9r4qg09c",
      "uynajfqv 2026-04-07T14:38:12Z ctx=131072 pp=317.7 tg=3 omlx=0.3.4 os=macOS 26.3.1 https://omlx.ai/benchmarks/uynajfqv"
    ],
    "upstreamUrls": [
      "https://omlx.ai/benchmarks/cwz701zg",
      "https://omlx.ai/benchmarks/43slutlr",
      "https://omlx.ai/benchmarks/uro6zorn",
      "https://omlx.ai/benchmarks/wxl6xasl",
      "https://omlx.ai/benchmarks/pk4gwdwa",
      "https://omlx.ai/benchmarks/9r4qg09c",
      "https://omlx.ai/benchmarks/uynajfqv"
    ]
  },
  "benchmark": {
    "tool": "oMLX",
    "outputFormat": "community API",
    "latencyMode": "single-user prompt/decode",
    "metadata": {
      "upstream_rows_in_group": 62,
      "selected_depths": 7,
      "latest_upstream_id": "pk4gwdwa",
      "latest_created_at": "2026-04-11T11:03:36Z",
      "selected_omlx_versions": "0.3.4, 0.3.5.dev2",
      "selected_os_versions": "macOS 26.3.1, macOS 26.4.1"
    }
  },
  "topology": {
    "acceleratorCount": 1,
    "os": "macOS 26.4.1",
    "runtimeVersions": {
      "omlx": "0.3.5.dev2"
    }
  },
  "source": {
    "kind": "community-benchmark",
    "title": "oMLX gemma-4-31B-it-oQ4 on M5 Max (40c) community benchmark",
    "url": "https://omlx.ai/benchmarks/pk4gwdwa",
    "raw": "data/upstream/omlx-benchmarks.jsonl",
    "license": "Apache-2.0 project; submitted benchmark data attribution required",
    "notes": "Generated from https://omlx.ai/benchmarks. Measurements link to their selected upstream oMLX benchmark rows."
  },
  "submitter": "oMLX community",
  "date": "2026-04-11",
  "status": "community",
  "notes": "Generated from the oMLX community benchmark API import. 62 upstream row(s) were scraped for this hardware/model/quant group; the latest row at each context depth was selected for simulation. Selected depths may span oMLX or macOS versions, and each measurement links to its exact upstream row."
}
